Release/_swigwrapper.cp36-win_amd64.exp
Release/_swigwrapper.cp36-win_amd64.lib
Release/swigwrapper_wrap.obj
mvs_ctcdecoder/__init__.py
mvs_ctcdecoder/_swigwrapper.cp36-win_amd64.pyd
mvs_ctcdecoder/swigwrapper.py
mvs_ctcdecoder-0.9.0a7.dist-info/COPYING
mvs_ctcdecoder-0.9.0a7.dist-info/LICENSE.paddlepaddle
mvs_ctcdecoder-0.9.0a7.dist-info/LICENSE.parlance
mvs_ctcdecoder-0.9.0a7.dist-info/METADATA
mvs_ctcdecoder-0.9.0a7.dist-info/WHEEL
mvs_ctcdecoder-0.9.0a7.dist-info/top_level.txt
mvs_ctcdecoder-0.9.0a7.dist-info/RECORD
