Metadata-Version: 2.1
Name: mvs-ctcdecoder
Version: 0.9.0a7
Summary: DS CTC decoder
Home-page: UNKNOWN
Author: UNKNOWN
Author-email: UNKNOWN
License: UNKNOWN
Platform: UNKNOWN
Requires-Dist: numpy (<1.14.5,>=1.12.0)
